cli/__init__.py
cli/commands.py
cli/heybud_cli.py
cli/init_commands.py
core/__init__.py
core/config.py
core/context.py
core/logger.py
core/orchestrator.py
core/parser.py
core/prompt_template.py
core/safety.py
core/types.py
core/prompt_templates/command_generation.yaml
core/prompt_templates/explain.yaml
core/prompt_templates/follow_up.yaml
core/provider/__init__.py
core/provider/anthropic_adapter.py
core/provider/base_adapter.py
core/provider/gemini_adapter.py
core/provider/huggingface_adapter.py
core/provider/local_llama_adapter.py
core/provider/noop_adapter.py
core/provider/ollama_adapter.py
core/provider/openai_adapter.py
heybud-0.0.1a1.dist-info/licenses/LICENSE
plugins/__init__.py
plugins/plugin_api.py
plugins/plugin_loader.py
plugins/filebud/__init__.py
plugins/gitbud/__init__.py
tests/__init__.py
tests/test_adapters.py
tests/test_integration.py
tests/test_parser.py
tests/test_safety.py
heybud-0.0.1a1.dist-info/METADATA
heybud-0.0.1a1.dist-info/WHEEL
heybud-0.0.1a1.dist-info/entry_points.txt
heybud-0.0.1a1.dist-info/top_level.txt
heybud-0.0.1a1.dist-info/RECORD
